MANIFEST.in
README.md
setup.py
pept3/__init__.py
pept3/__main__.py
pept3/bio.py
pept3/dataset.py
pept3/features.py
pept3/finetune.py
pept3/main.py
pept3/models.py
pept3/similarity.py
pept3/utils.py
pept3.egg-info/PKG-INFO
pept3.egg-info/SOURCES.txt
pept3.egg-info/dependency_links.txt
pept3.egg-info/entry_points.txt
pept3.egg-info/requires.txt
pept3.egg-info/top_level.txt