Metadata-Version: 2.1
Name: pept3
Version: 0.0.1
Summary: Test-time training for deep MS/MS spectrum prediction improves peptide identification
Home-page: https://github.com/gusye1234/PepT3
Author: JianbaiYe
License: UNKNOWN
Platform: UNKNOWN
Classifier: Programming Language :: Python :: 3
Classifier: License :: OSI Approved :: MIT License
Classifier: Operating System :: OS Independent
Requires-Python: >=3.6
